{"address1": "6001 Bollinger Canyon Road", "city": "San Ramon", "state": "CA", "zip": "94583-2324", "country": "United States", "phone": "925 842 1000", "website": "https://www.chevron.com", "industry": "Oil & Gas Integrated", "industryKey": "oil-gas-integrated", "industryDisp": "Oil & Gas Integrated", "sector": "Energy", "sectorKey": "energy", "sectorDisp": "Energy", "longBusinessSummary": "Chevron Corporation, through its subsidiaries, engages in the integrated energy and chemicals operations in the United States and internationally. The company operates in two segments, Upstream and Downstream. The Upstream segment is involved in the exploration, development, production, and transportation of crude oil and natural gas; processing, liquefaction, transportation, and regasification of liquefied natural gas; transportation of crude oil through pipelines; transportation, storage, and marketing of natural gas; and carbon capture and storage, as well as a gas-to-liquids plant. The Downstream segment refines crude oil into petroleum products; markets crude oil, refined products, and lubricants; manufactures and markets renewable fuels, commodity petrochemicals, plastics for industrial uses, and fuel and lubricant additives; and transports crude oil and refined products by pipeline, marine vessel, motor equipment, and rail car. The company was formerly known as ChevronTexaco Corporation and changed its name to Chevron Corporation in 2005. Chevron Corporation was founded in 1879 and is headquartered in San Ramon, California.", "fullTimeEmployees": 45600, "companyOfficers": [{"maxAge": 1, "name": "Mr. Michael K. Wirth", "age": 62, "title": "Chairman & CEO", "yearBorn": 1961, "fiscalYear": 2023, "totalPay": {"raw": 4865200, "fmt": "4.87M", "longFmt": "4,865,200"}, "exercisedValue": {"raw": 0, "fmt": null, "longFmt": "0"}, "unexercisedValue": {"raw": 64144600, "fmt": "64.14M", "longFmt": "64,144,600"}}, {"maxAge": 1, "name": "Mr. R. Hewitt Pate", "age": 60, "title": "VP & General Counsel", "yearBorn": 1963, "fiscalYear": 2023, "totalPay": {"raw": 2383101, "fmt": "2.38M", "longFmt": "2,383,101"}, "exercisedValue": {"raw": 0, "fmt": null, "longFmt": "0"}, "unexercisedValue": {"raw": 7535996, "fmt": "7.54M", "longFmt": "7,535,996"}}, {"maxAge": 1, "name": "Mr. A. Nigel Hearne", "age": 55, "title": "Executive Vice President of Oil, Products & Gas", "yearBorn": 1968, "fiscalYear": 2023, "totalPay": {"raw": 3390193, "fmt": "3.39M", "longFmt": "3,390,193"}, "exercisedValue": {"raw": 0, "fmt": null, "longFmt": "0"}, "unexercisedValue": {"raw": 2182150, "fmt": "2.18M", "longFmt": "2,182,150"}}, {"maxAge": 1, "name": "Ms. Eimear P. Bonner", "age": 48, "title": "VP, CFO, & President of Chevron Technical Center", "yearBorn": 1975, "fiscalYear": 2023, "exercisedValue": {"raw": 0, "fmt": null, "longFmt": "0"}, "unexercisedValue": {"raw": 0, "fmt": null, "longFmt": "0"}}, {"maxAge": 1, "name": "Ms. Rhonda J. Morris", "age": 58, "title": "VP & Chief Human Resources Officer", "yearBorn": 1965, "fiscalYear": 2023, "exercisedValue": {"raw": 0, "fmt": null, "longFmt": "0"}, "unexercisedValue": {"raw": 0, "fmt": null, "longFmt": "0"}}, {"maxAge": 1, "name": "Mr. Clay  Neff", "age": 61, "title": "President of International Exploration & Production", "yearBorn": 1962, "fiscalYear": 2023, "exercisedValue": {"raw": 0, "fmt": null, "longFmt": "0"}, "unexercisedValue": {"raw": 0, "fmt": null, "longFmt": "0"}}, {"maxAge": 1, "name": "Mr. Jeff B. Gustavson", "age": 50, "title": "President of Chevron New Energies & VP of Lower Carbon Energies", "yearBorn": 1973, "fiscalYear": 2023, "exercisedValue": {"raw": 0, "fmt": null, "longFmt": "0"}, "unexercisedValue": {"raw": 0, "fmt": null, "longFmt": "0"}}, {"maxAge": 1, "name": "Dr. Anoop  Kumar", "title": "President of the National Lubricating Grease", "fiscalYear": 2023, "exercisedValue": {"raw": 0, "fmt": null, "longFmt": "0"}, "unexercisedValue": {"raw": 0, "fmt": null, "longFmt": "0"}}, {"maxAge": 1, "name": "Ms. Molly T. Laegeler", "age": 45, "title": "VP of Strategy & Sustainability", "yearBorn": 1978, "fiscalYear": 2023, "exercisedValue": {"raw": 0, "fmt": null, "longFmt": "0"}, "unexercisedValue": {"raw": 0, "fmt": null, "longFmt": "0"}}, {"maxAge": 1, "name": "Mr. Paul K. Siegele", "age": 64, "title": "CTO & President - Chevron Energy Technology Company", "yearBorn": 1959, "fiscalYear": 2023, "exercisedValue": {"raw": 0, "fmt": null, "longFmt": "0"}, "unexercisedValue": {"raw": 0, "fmt": null, "longFmt": "0"}}], "auditRisk": 3, "boardRisk": 4, "compensationRisk": 2, "shareHolderRightsRisk": 1, "overallRisk": 1, "governanceEpochDate": 1711929600, "compensationAsOfEpochDate": 1703980800, "maxAge": 86400, "priceHint": 2, "previousClose": 157.57, "open": 158.75, "dayLow": 158.1495, "dayHigh": 160.75, "regularMarketPreviousClose": 157.57, "regularMarketOpen": 158.75, "regularMarketDayLow": 158.1495, "regularMarketDayHigh": 160.75, "dividendRate": 6.52, "dividendYield": 0.040799998, "exDividendDate": 1707955200, "payoutRatio": 0.53169996, "fiveYearAvgDividendYield": 4.42, "beta": 1.129, "trailingPE": 14.084508, "forwardPE": 11.721612, "volume": 7592864, "regularMarketVolume": 7592864, "averageVolume": 8331482, "averageVolume10days": 7232270, "averageDailyVolume10Day": 7232270, "bid": 0.0, "ask": 0.0, "bidSize": 800, "askSize": 900, "marketCap": 295385595904, "fiftyTwoWeekLow": 139.62, "fiftyTwoWeekHigh": 172.38, "priceToSalesTrailing12Months": 1.516361, "fiftyDayAverage": 155.2882, "twoHundredDayAverage": 154.95865, "trailingAnnualDividendRate": 6.04, "trailingAnnualDividendYield": 0.038332168, "currency": "USD", "fromCurrency": null, "toCurrency": null, "lastMarket": null, "coinMarketCapLink": null, "algorithm": null, "tradeable": false, "enterpriseValue": 315982053376, "profitMargins": 0.1097, "floatShares": 1727650345, "sharesOutstanding": 1846160000, "sharesShort": 49670617, "sharesShortPriorMonth": 51737331, "sharesShortPreviousMonthDate": 1709164800, "dateShortInterest": 1711584000, "sharesPercentSharesOut": 0.026700001, "heldPercentInsiders": 0.0688, "heldPercentInstitutions": 0.66893, "shortRatio": 5.71, "shortPercentOfFloat": 0.026700001, "impliedSharesOutstanding": 1862800000, "category": null, "bookValue": 86.274, "priceToBook": 1.8545563, "fundFamily": null, "legalType": null, "lastFiscalYearEnd": 1703980800, "nextFiscalYearEnd": 1735603200, "mostRecentQuarter": 1703980800, "earningsQuarterlyGrowth": -0.644, "netIncomeToCommon": 21368999936, "trailingEps": 11.36, "forwardEps": 13.65, "pegRatio": 7.23, "lastSplitFactor": "2:1", "lastSplitDate": 1095033600, "enterpriseToRevenue": 1.622, "enterpriseToEbitda": 7.492, "52WeekChange": -0.066946566, "SandP52WeekChange": 0.2006725, "lastDividendValue": 1.63, "lastDividendDate": 1707955200, "exchange": "NYQ", "quoteType": "EQUITY", "symbol": "CVX", "underlyingSymbol": "CVX", "shortName": "Chevron Corporation", "longName": "Chevron Corporation", "firstTradeDateEpochUtc": -252322200, "timeZoneFullName": "America/New_York", "timeZoneShortName": "EDT", "uuid": "030410ed-236a-3375-b5de-4212d6028be6", "messageBoardId": "finmb_98506", "gmtOffSetMilliseconds": -14400000, "currentPrice": 160.0, "targetHighPrice": 191.65, "targetLowPrice": 139.04, "targetMeanPrice": 170.2, "targetMedianPrice": 171.52, "recommendationMean": 2.1, "recommendationKey": "buy", "numberOfAnalystOpinions": 23, "totalCash": 8223000064, "totalCashPerShare": 4.427, "ebitda": 42176999424, "totalDebt": 26069999616, "quickRatio": 0.868, "currentRatio": 1.275, "totalRevenue": 194798993408, "debtToEquity": 16.1, "revenuePerShare": 104.004, "returnOnAssets": 0.064899996, "returnOnEquity": 0.13292, "freeCashflow": 14623375360, "operatingCashflow": 35609001984, "earningsGrowth": -0.636, "revenueGrowth": -0.154, "grossMargins": 0.39286998, "ebitdaMargins": 0.21652001, "operatingMargins": 0.105900005, "financialCurrency": "USD"}